agentype/__init__.py
agentype/servers.py
agentype/api/__init__.py
agentype/api/annotation.py
agentype/api/celltype_analysis.py
agentype/api/data_processing.py
agentype/api/main_workflow.py
agentype/appagent/__init__.py
agentype/appagent/example_usage.py
agentype/appagent/mcp_client_example.py
agentype/appagent/agent/__init__.py
agentype/appagent/agent/celltype_annotation_agent.py
agentype/appagent/api/main.py
agentype/appagent/api/models.py
agentype/appagent/api/routes.py
agentype/appagent/api/service.py
agentype/appagent/clients/__init__.py
agentype/appagent/clients/mcp_client.py
agentype/appagent/config/__init__.py
agentype/appagent/config/cache_config.py
agentype/appagent/config/prompts.py
agentype/appagent/config/settings.py
agentype/appagent/llm/__init__.py
agentype/appagent/locales/en.json
agentype/appagent/locales/zh.json
agentype/appagent/services/__init__.py
agentype/appagent/services/mcp_server.py
agentype/appagent/tools/celldex_download_tool.py
agentype/appagent/tools/celldex_info_tool.py
agentype/appagent/tools/celltypist_simple.py
agentype/appagent/tools/file_validators.py
agentype/appagent/tools/get_celldex_projects_bilingual.py
agentype/appagent/tools/get_celltypist_models.py
agentype/appagent/tools/get_sctype_tissues.py
agentype/appagent/tools/run_sctype_test.py
agentype/appagent/tools/sctype_simple.py
agentype/appagent/tools/singleR_simple.py
agentype/appagent/tools/species_detection.py
agentype/appagent/tools/test_file_format_fallback.py
agentype/appagent/tools/r/__init__.py
agentype/appagent/tools/r/sctype_run.R
agentype/appagent/tools/r/sctype/ScTypeDB_full.xlsx
agentype/appagent/tools/r/sctype/__init__.py
agentype/appagent/tools/r/sctype/auto_detect_tissue_type.R
agentype/appagent/tools/r/sctype/gene_sets_prepare.R
agentype/appagent/tools/r/sctype/sctype_score_.R
agentype/appagent/tools/r/sctype/sctype_wrapper.R
agentype/appagent/utils/__init__.py
agentype/appagent/utils/common.py
agentype/appagent/utils/content_processor.py
agentype-1.0.1.dist-info/licenses/LICENSE
agentype-1.0.1.dist-info/METADATA
agentype-1.0.1.dist-info/WHEEL
agentype-1.0.1.dist-info/entry_points.txt
agentype-1.0.1.dist-info/top_level.txt
agentype-1.0.1.dist-info/RECORD
