Metadata-Version: 2.4
Name: agentype
Version: 1.0.1
Summary: 统一的细胞类型分析工具包，集成四个专业Agent提供完整的细胞类型注释流程
Home-page: https://github.com/agentype/celltype-agent
Author: CellType Agent Team
Author-email: CellType Agent Team <contact@agentype.com>
License: MIT License
Project-URL: Homepage, https://github.com/agentype/celltype-agent
Project-URL: Bug Tracker, https://github.com/agentype/celltype-agent/issues
Project-URL: Documentation, https://github.com/agentype/celltype-agent/wiki
Project-URL: Source, https://github.com/agentype/celltype-agent
Project-URL: Changelog, https://github.com/agentype/celltype-agent/blob/main/CHANGELOG.md
Keywords: single-cell,RNA-seq,cell-type,annotation,SingleR,scType,CellTypist,bioinformatics,genomics,MCP
Platform: any
Classifier: Development Status :: 4 - Beta
Classifier: Intended Audience :: Science/Research
Classifier: Topic :: Scientific/Engineering :: Bio-Informatics
Classifier: License :: OSI Approved :: MIT License
Classifier: Programming Language :: Python :: 3
Classifier: Programming Language :: Python :: 3.8
Classifier: Programming Language :: Python :: 3.9
Classifier: Programming Language :: Python :: 3.10
Classifier: Programming Language :: Python :: 3.11
Classifier: Programming Language :: Python :: 3.12
Classifier: Operating System :: OS Independent
Classifier: Natural Language :: Chinese (Simplified)
Classifier: Natural Language :: English
Requires-Python: >=3.8
License-File: LICENSE
Requires-Dist: mcp>=1.0.0
Requires-Dist: fastmcp>=0.3.0
Requires-Dist: fastapi>=0.104.0
Requires-Dist: uvicorn[standard]>=0.24.0
Requires-Dist: pydantic>=2.5.0
Requires-Dist: asyncio-mqtt>=0.16.0
Requires-Dist: aiofiles>=23.2.1
Requires-Dist: websockets>=12.0
Requires-Dist: numpy<2.0,>=1.24.0
Requires-Dist: pandas<2.2.0,>=2.1.0
Requires-Dist: scipy>=1.11.0
Requires-Dist: scanpy>=1.9.0
Requires-Dist: anndata>=0.10.0
Requires-Dist: gseapy>=1.1.0
Requires-Dist: h5py>=3.10.0
Requires-Dist: tables>=3.9.0
Requires-Dist: openpyxl>=3.1.0
Requires-Dist: requests>=2.31.0
Requires-Dist: httpx>=0.25.0
Requires-Dist: pyyaml>=6.0
Requires-Dist: jsonschema>=4.20.0
Requires-Dist: loguru>=0.7.0
Requires-Dist: click>=8.1.0
Requires-Dist: rich>=13.7.0
Requires-Dist: tqdm>=4.66.0
Requires-Dist: pathlib2>=2.3.7
Requires-Dist: filetype>=1.2.0
Requires-Dist: typing-extensions>=4.8.0
Requires-Dist: pydantic-settings>=2.1.0
Requires-Dist: babel>=2.13.0
Requires-Dist: python-i18n>=0.3.9
Requires-Dist: psutil>=5.9.0
Requires-Dist: python-dateutil>=2.8.0
Requires-Dist: pytz>=2023.3
Provides-Extra: annotation
Requires-Dist: celltypist>=1.6.0; extra == "annotation"
Requires-Dist: rpy2>=3.5.0; extra == "annotation"
Requires-Dist: bioservices>=1.11.0; extra == "annotation"
Requires-Dist: biopython>=1.81; extra == "annotation"
Provides-Extra: ml
Requires-Dist: scikit-learn>=1.3.0; extra == "ml"
Requires-Dist: torch>=2.0.0; extra == "ml"
Requires-Dist: numba>=0.58.0; extra == "ml"
Provides-Extra: viz
Requires-Dist: matplotlib>=3.8.0; extra == "viz"
Requires-Dist: seaborn>=0.12.0; extra == "viz"
Requires-Dist: plotly>=5.17.0; extra == "viz"
Provides-Extra: performance
Requires-Dist: dask[complete]>=2023.12.0; extra == "performance"
Requires-Dist: joblib>=1.3.0; extra == "performance"
Requires-Dist: diskcache>=5.6.0; extra == "performance"
Provides-Extra: deploy
Requires-Dist: gunicorn>=21.2.0; extra == "deploy"
Requires-Dist: docker>=6.1.0; extra == "deploy"
Provides-Extra: dev
Requires-Dist: pytest>=7.4.0; extra == "dev"
Requires-Dist: pytest-asyncio>=0.21.0; extra == "dev"
Requires-Dist: pytest-cov>=4.1.0; extra == "dev"
Requires-Dist: black>=23.11.0; extra == "dev"
Requires-Dist: flake8>=6.1.0; extra == "dev"
Requires-Dist: mypy>=1.7.0; extra == "dev"
Requires-Dist: ruff>=0.1.0; extra == "dev"
Provides-Extra: all
Requires-Dist: agentype[annotation,deploy,ml,performance,viz]; extra == "all"
Dynamic: author
Dynamic: home-page
Dynamic: license-file
Dynamic: platform
Dynamic: requires-python
